[{"avtor":"<a href='\/@\/fish224\/'>fish224<\/a>","rtg":1500,"try":4,"success":4,"uslovie":"\u0421\u043a\u043e\u043b\u044c\u043a\u043e \u0431\u0443\u0434\u0435\u0442 2 + 2?","ans":"4","tried_by":["fish224","Guest1729000","ma3rx","Filin0613"]},{"avtor":"<a href='\/@\/fish224\/'>fish224<\/a>","rtg":1500,"try":4,"success":3,"uslovie":"\u0421\u043a\u043e\u043b\u044c\u043a\u043e \u0431\u0443\u0434\u0435\u0442 7 + 2?","ans":"9","tried_by":["fish224","ma3rx","Vitalik1214","Vitalik1214"]},{"avtor":"<a href='\/@\/fish224\/'>fish224<\/a>","rtg":1500,"try":9,"success":9,"uslovie":"\u0421\u043a\u043e\u043b\u044c\u043a\u043e \u0431\u0443\u0434\u0435\u0442 $$4^2$$?","ans":"16","tried_by":["fish224","ma3rx","ma3rx","fish224","fish224","fish224","ma3rx","Vitalik1214","fish224"]},{"avtor":"<a href='\/@\/fish224\/'>fish224<\/a>","rtg":1500,"try":5,"success":5,"uslovie":"\u0421\u043a\u043e\u043b\u044c\u043a\u043e \u0431\u0443\u0434\u0435\u0442 100 \/ 4?","ans":"25","tried_by":["fish224","fish224","ma3rx","fish224","fish224"]},{"avtor":"<a href='\/@\/fish224\/'>fish224<\/a>","rtg":1500,"try":4,"success":3,"uslovie":"\u0421\u043a\u043e\u043b\u044c\u043a\u043e \u0431\u0443\u0434\u0435\u0442 32 + 4?","ans":"36","tried_by":["fish224","fish224","fish224","Vitalik1214"]},{"avtor":"<a href='\/@\/fish224\/'>fish224<\/a>","rtg":1500,"try":7,"success":6,"uslovie":"\u0421\u043a\u043e\u043b\u044c\u043a\u043e \u0431\u0443\u0434\u0435\u0442 60 - 11?","ans":"49","tried_by":["fish224","fish224","fish224","ma3rx","fish224","Vitalik1214","Vitalik1214"]}]